yf_templates/__init__.py
yf_templates/apps.py
yf_templates/static/authentication/img/yulai-federation/background.jpg
yf_templates/static/icons/yulai-federation/allianceauth.png
yf_templates/static/icons/yulai-federation/apple-touch-icon.png
yf_templates/static/icons/yulai-federation/favicon-16x16.png
yf_templates/static/icons/yulai-federation/favicon-32x32.png
yf_templates/static/icons/yulai-federation/favicon-96x96.png
yf_templates/static/img/yulai-federation/yulai-logo-320.png
yf_templates/static/yf_templates/css/yulai-federation.css
yf_templates/static/yf_templates/css/yulai-federation.min.css
yf_templates/templates/allianceauth/icons.html
yf_templates/templates/allianceauth/top-menu.html
yf_templates/templates/bundles/svg/ccp_sso.svg
yf_templates/templates/public/base.html
yf_templates/templates/public/lang_select.html
yf_templates/templates/public/login.html
yf_templates/templates/public/middle_box.html
yf_templates/templates/public/register.html
yf_templates/templates/registration/activate.html
yf_templates/templates/registration/registration_form.html
yf_templates-0.3.0.dist-info/LICENSE
yf_templates-0.3.0.dist-info/METADATA
yf_templates-0.3.0.dist-info/WHEEL
yf_templates-0.3.0.dist-info/top_level.txt
yf_templates-0.3.0.dist-info/RECORD
