Metadata-Version: 2.1
Name: yf-templates
Version: 0.3.0
Summary: Yulai Federation Template Overrides for Alliance Auth
Home-page: https://github.com/yulai-federation/yf-auth-templates
Author: Peter Pfeufer
Author-email: development@ppfeufer.de
Maintainer: Peter Pfeufer
Maintainer-email: development@ppfeufer.de
License: GPL-2.0
Project-URL: Issue / Bug Reports, https://github.com/yulai-federation/yf-auth-templates/issues
Project-URL: Changelog, https://github.com/yulai-federation/yf-auth-templates/blob/master/CHANGELOG.md
Keywords: allianceauth,eveonline,template,template_override,yulai_federation
Classifier: Environment :: Web Environment
Classifier: Framework :: Django
Classifier: Framework :: Django :: 4.0
Classifier: Intended Audience :: Developers
Classifier: License :: OSI Approved :: GNU General Public License v2 (GPLv2)
Classifier: License :: OSI Approved :: GNU General Public License v3 (GPLv3)
Classifier: Operating System :: OS Independent
Classifier: Programming Language :: Python
Classifier: Programming Language :: Python :: 3
Classifier: Programming Language :: Python :: 3.8
Classifier: Programming Language :: Python :: 3.9
Classifier: Programming Language :: Python :: 3.10
Classifier: Programming Language :: Python :: 3.11
Classifier: Topic :: Internet :: WWW/HTTP
Classifier: Topic :: Internet :: WWW/HTTP :: Dynamic Content
Requires-Python: ~=3.8
License-File: LICENSE
Requires-Dist: allianceauth (>=3.0.0)
